batch_inference/__init__.py
batch_inference/batch_context.py
batch_inference/decorators.py
batch_inference/logger.py
batch_inference/model_host.py
batch_inference/remote_model_host.py
batch_inference/aio/__init__.py
batch_inference/aio/batch_context.py
batch_inference/aio/model_host.py
batch_inference/aio/remote_model_host/__init__.py
batch_inference/aio/remote_model_host/model_host_client.py
batch_inference/aio/remote_model_host/model_host_pb2.py
batch_inference/aio/remote_model_host/model_host_pb2_grpc.py
batch_inference/aio/remote_model_host/model_host_server.py
batch_inference/aio/remote_model_host/msgpack_serialization.py
batch_inference/aio/remote_model_host/remote_model_host.py
batch_inference/batcher/__init__.py
batch_inference/batcher/batcher.py
batch_inference/batcher/bucket_seq_batcher.py
batch_inference/batcher/concat_batcher.py
batch_inference/batcher/multi_batcher.py
batch_inference/batcher/seq_batcher.py
batch_inference/batcher/tensor_ops_np.py
batch_inference/batcher/tensor_ops_pt.py
batch_inference-1.0.dist-info/LICENSE
batch_inference-1.0.dist-info/METADATA
batch_inference-1.0.dist-info/WHEEL
batch_inference-1.0.dist-info/top_level.txt
batch_inference-1.0.dist-info/RECORD
