Metadata-Version: 2.1
Name: batch-inference
Version: 1.0
Summary: Batch Inference
Author-email: Yong Huang <yohuan@microsoft.com>, Xi Chen <xichen5@microsoft.com>, Lu Ye <luye@microsoft.com>, Ze Tao <zetao@microsoft.com>
Project-URL: Homepage, https://github.com/microsoft/batch-inference.git
Classifier: Programming Language :: Python :: 3
Classifier: License :: OSI Approved :: MIT License
Classifier: Operating System :: OS Independent
Requires-Python: >=3.8
License-File: LICENSE
Requires-Dist: filelock
Requires-Dist: grpcio
Requires-Dist: msgpack
Requires-Dist: msgpack-numpy
Requires-Dist: numpy
Requires-Dist: protobuf
Provides-Extra: docs
Requires-Dist: flask (>=2.0.2) ; extra == 'docs'
Requires-Dist: furo (>=2022.12.7) ; extra == 'docs'
Requires-Dist: sphinx (>=6.1.3) ; extra == 'docs'
Requires-Dist: sphinx-autodoc-typehints (!=1.23.4,>=1.22) ; extra == 'docs'
Requires-Dist: sphinx-rtd-theme ; extra == 'docs'
Requires-Dist: myst-parser ; extra == 'docs'
Requires-Dist: sphinxemoji ; extra == 'docs'
Requires-Dist: transformers (>=4.27.4) ; extra == 'docs'
Requires-Dist: chardet (>=5.1.0) ; extra == 'docs'
Provides-Extra: testing
Requires-Dist: onnxruntime ; extra == 'testing'
Requires-Dist: pytest (>=7.2.2) ; extra == 'testing'
Requires-Dist: torch ; extra == 'testing'
Requires-Dist: transformers (>=4.27.4) ; extra == 'testing'
